{
	"archive" : {},
	"artifacts" : 
	[
		{
			"path" : "libs/dept/libDept.a"
		}
	],
	"backtrace" : 1,
	"backtraceGraph" : 
	{
		"commands" : 
		[
			"add_library"
		],
		"files" : 
		[
			"libs/dept/CMakeLists.txt"
		],
		"nodes" : 
		[
			{
				"file" : 0
			},
			{
				"command" : 0,
				"file" : 0,
				"line" : 1,
				"parent" : 0
			}
		]
	},
	"compileGroups" : 
	[
		{
			"compileCommandFragments" : 
			[
				{
					"fragment" : "-g -isysroot /Library/Developer/CommandLineTools/SDKs/MacOSX26.2.sdk   -std=c++11"
				}
			],
			"language" : "CXX",
			"sourceIndexes" : 
			[
				0
			]
		}
	],
	"id" : "Dept::@94b67ab9eeb025deefa8",
	"name" : "Dept",
	"nameOnDisk" : "libDept.a",
	"paths" : 
	{
		"build" : "libs/dept",
		"source" : "libs/dept"
	},
	"sourceGroups" : 
	[
		{
			"name" : "Source Files",
			"sourceIndexes" : 
			[
				0
			]
		}
	],
	"sources" : 
	[
		{
			"backtrace" : 1,
			"compileGroupIndex" : 0,
			"path" : "libs/dept/Dept.cpp",
			"sourceGroupIndex" : 0
		}
	],
	"type" : "STATIC_LIBRARY"
}
